m_sixteen_bit_adder.v
module sixteen_bit_adder(
    input [15:0] a,
    input [15:0] b,
    input cin,
    output [15:0] sum,
    output cout
);
    assign {cout, sum} = a + b + cin;
endmodule

m_dff_16bit.v
module dff_16bit (
    input      [15:0] d,
    input             clk,
    input             rstn,
    input             en,
    output reg [15:0] q
);
    always @(posedge clk) begin
        if (!rstn)
            q <= 16'b0;
        else if (en)
            q <= d;
    end
endmodule

m_system.v
module system (
    // 寄存器输入端口
    input      [15:0] d_a,      // 第一个操作数输入
    input      [15:0] d_b,      // 第二个操作数输入
    input             clk,
    input             rstn,
    input             en_a,      // 第一个寄存器使能
    input             en_b,      // 第二个寄存器使能
    
    // 加法器其他输入端口
    input             cin,
    
    // 系统输出端口
    output     [15:0] sum,
    output            cout
);
    
    // 内部连线：两个寄存器的输出
    wire [15:0] q_a;
    wire [15:0] q_b;
    
    // 1. 实例化第一个16位寄存器（存储操作数a）
    dff_16bit register_a_inst (
        .d   (d_a),
        .clk (clk),
        .rstn(rstn),
        .en  (en_a),
        .q   (q_a)
    );
    
    // 2. 实例化第二个16位寄存器（存储操作数b）
    dff_16bit register_b_inst (
        .d   (d_b),
        .clk (clk),
        .rstn(rstn),
        .en  (en_b),
        .q   (q_b)
    );
    
    // 3. 实例化16位加法器
    sixteen_bit_adder adder_inst (
        .a   (q_a),    // 从寄存器A输出读取
        .b   (q_b),    // 从寄存器B输出读取
        .cin (cin),
        .sum (sum),
        .cout(cout)
    );
    
endmodule

tb.v
module tb_system;
    reg  [15:0] d_a, d_b;
    reg clk=0, rstn, en_a, en_b, cin;  // clk初始化
    wire [15:0] sum;
    wire cout;
    
    system uut (
        .d_a(d_a),
        .d_b(d_b),
        .clk(clk),
        .rstn(rstn),
        .en_a(en_a),
        .en_b(en_b),
        .cin(cin),
        .sum(sum),
        .cout(cout)
    );
    
    // 波形记录（先于clk翻转）
    initial begin
        $dumpfile("wave.vcd");
        $dumpvars(0, tb_system);
    end
    
    initial forever #5 clk = ~clk;
    
    initial begin
        d_a=0; d_b=0; cin=0; en_a=0; en_b=0;
        rstn=0; #15; rstn=1; #10;        // 复位
        
        // 测试1：同时写入两个寄存器并进行加法
        d_a=123; d_b=100; en_a=1; en_b=1; #10;
        $display("t=%0t: 123+100=%0d", $time, sum);
        
        // 测试2：只更新b寄存器的值，a保持原值
        en_a=0; en_b=1; d_b=200; #10;
        $display("t=%0t: 123+200=%0d", $time, sum);
        
        // 测试3：同时更新两个寄存器，测试溢出
        d_a=65535; d_b=1; en_a=1; en_b=1; #10;
        $display("t=%0t: 65535+1=%0d cout=%0d", $time, sum, cout);
        
        // 测试4：只更新a寄存器
        d_a=50; d_b=25; en_a=1; en_b=0; #10;
        $display("t=%0t: 50+1=%0d", $time, sum);  // b仍为1
        
        // 测试5：同时更新两个寄存器
        d_a=100; d_b=200; en_a=1; en_b=1; #10;
        $display("t=%0t: 100+200=%0d", $time, sum);
        
        // 测试6：复位测试
        rstn=0; #10;
        $display("t=%0t: 复位后0+0=%0d", $time, sum);
        
        #10; $finish;
    end
endmodule

wave.vcd
$date
	Thu Jan 08 09:51:55 2026
$end
$version
	Icarus Verilog
$end
$timescale
	1s
$end
$scope module tb_system $end
$var wire 16 ! sum [15:0] $end
$var wire 1 " cout $end
$var reg 1 # cin $end
$var reg 1 $ clk $end
$var reg 16 % d_a [15:0] $end
$var reg 16 & d_b [15:0] $end
$var reg 1 ' en_a $end
$var reg 1 ( en_b $end
$var reg 1 ) rstn $end
$scope module uut $end
$var wire 1 # cin $end
$var wire 1 $ clk $end
$var wire 16 * d_a [15:0] $end
$var wire 16 + d_b [15:0] $end
$var wire 1 ' en_a $end
$var wire 1 ( en_b $end
$var wire 1 ) rstn $end
$var wire 16 , sum [15:0] $end
$var wire 16 - q_b [15:0] $end
$var wire 16 . q_a [15:0] $end
$var wire 1 " cout $end
$scope module adder_inst $end
$var wire 1 # cin $end
$var wire 16 / sum [15:0] $end
$var wire 1 " cout $end
$var wire 16 0 b [15:0] $end
$var wire 16 1 a [15:0] $end
$upscope $end
$scope module register_a_inst $end
$var wire 1 $ clk $end
$var wire 16 2 d [15:0] $end
$var wire 1 ' en $end
$var wire 1 ) rstn $end
$var reg 16 3 q [15:0] $end
$upscope $end
$scope module register_b_inst $end
$var wire 1 $ clk $end
$var wire 16 4 d [15:0] $end
$var wire 1 ( en $end
$var wire 1 ) rstn $end
$var reg 16 5 q [15:0] $end
$upscope $end
$upscope $end
$upscope $end
$enddefinitions $end
#0
$dumpvars
bx 5
b0 4
bx 3
b0 2
bx 1
bx 0
bx /
bx .
bx -
bx ,
b0 +
b0 *
0)
0(
0'
b0 &
b0 %
0$
0#
x"
bx !
$end
#5
b0 !
b0 ,
b0 /
0"
b0 .
b0 1
b0 3
b0 -
b0 0
b0 5
1$
#10
0$
#15
1$
1)
#20
0$
#25
b11011111 !
b11011111 ,
b11011111 /
b1111011 .
b1111011 1
b1111011 3
b1100100 -
b1100100 0
b1100100 5
1$
1(
1'
b1100100 &
b1100100 +
b1100100 4
b1111011 %
b1111011 *
b1111011 2
#30
0$
#35
b101000011 !
b101000011 ,
b101000011 /
b11001000 -
b11001000 0
b11001000 5
1$
b11001000 &
b11001000 +
b11001000 4
0'
#40
0$
#45
1"
b0 !
b0 ,
b0 /
b1111111111111111 .
b1111111111111111 1
b1111111111111111 3
b1 -
b1 0
b1 5
1$
1'
b1 &
b1 +
b1 4
b1111111111111111 %
b1111111111111111 *
b1111111111111111 2
#50
0$
#55
b110011 !
b110011 ,
b110011 /
0"
b110010 .
b110010 1
b110010 3
1$
0(
b11001 &
b11001 +
b11001 4
b110010 %
b110010 *
b110010 2
#60
0$
#65
b100101100 !
b100101100 ,
b100101100 /
b1100100 .
b1100100 1
b1100100 3
b11001000 -
b11001000 0
b11001000 5
1$
1(
b11001000 &
b11001000 +
b11001000 4
b1100100 %
b1100100 *
b1100100 2
#70
0$
#75
b0 !
b0 ,
b0 /
b0 -
b0 0
b0 5
b0 .
b0 1
b0 3
1$
0)
