jiajianchengchudff.v
module subtractor_16bits(
    input [15:0] a,
    input [15:0] b,
    input bin,
    output [15:0] diff,
    output bout
);
    assign {bout, diff} = a - b - bin;
endmodule

module adder_16bits(
    input [15:0] a,
    input [15:0] b,
    input cin,
    output [15:0] sum,
    output cout
);
    assign {cout, sum} = a + b + cin;
endmodule

module multiplier_16bits(
    input [15:0] a,
    input [15:0] b,
    output [31:0] product
);
    assign product = a * b;
endmodule

module divider_16bits(
    input [15:0] dividend,
    input [15:0] divisor,
    output [15:0] quotient,
    output [15:0] remainder
);
    assign quotient = dividend / divisor;
    assign remainder = dividend % divisor;
endmodule

module dff_16bit (
    input      [15:0] d,
    input             clk,
    input             rstn,
    input             en,
    output reg [15:0] q
);
    always @(posedge clk) begin
        if (!rstn)
            q <= 16'b0;
        else if (en)
            q <= d;
    end
endmodule

system_adder.v
module system_adder (
    // 寄存器输入端口
    input      [15:0] d_a,      // 操作数A输入
    input      [15:0] d_b,      // 操作数B输入
    input             clk,
    input             rstn,
    input             en_a,      // A寄存器使能
    input             en_b,      // B寄存器使能
    input             en_result, // 新增：结果寄存器使能
    
    // 加法器其他输入端口
    input             cin,
    
    // 系统输出端口
    output     [15:0] result,    // 改为：存储的结果输出
    output            cout
);
    
    // 内部连线
    wire [15:0] q_a;      // 寄存器A输出
    wire [15:0] q_b;      // 寄存器B输出
    wire [15:0] sum_wire; // 加法器直接输出
    wire [15:0] q_result; // 结果寄存器输出
    
    // 1. 实例化第一个16位寄存器（操作数A）
    dff_16bit register_a_inst (
        .d   (d_a),
        .clk (clk),
        .rstn(rstn),
        .en  (en_a),
        .q   (q_a)
    );
    
    // 2. 实例化第二个16位寄存器（操作数B）
    dff_16bit register_b_inst (
        .d   (d_b),
        .clk (clk),
        .rstn(rstn),
        .en  (en_b),
        .q   (q_b)
    );
    
    // 3. 实例化16位加法器
    adder_16bits adder_inst (
        .a   (q_a),
        .b   (q_b),
        .cin (cin),
        .sum (sum_wire),      // 连接到中间线
        .cout(cout)
    );
    
    // 4. 实例化第三个16位寄存器（存储结果）
    dff_16bit result_register_inst (
        .d   (sum_wire),      
        .clk (clk),
        .rstn(rstn),
        .en  (en_result),     
        .q   (q_result)       
    );

    assign result = q_result;
    
endmodule

tb_adder.v
module tb_adder;
    reg  [15:0] d_a, d_b;
    reg clk=0, rstn, en_a, en_b, en_result, cin;
    wire [15:0] result;
    wire cout;
    
    system_adder uut (
        .d_a(d_a),
        .d_b(d_b),
        .clk(clk),
        .rstn(rstn),
        .en_a(en_a),
        .en_b(en_b),
        .en_result(en_result),
        .cin(cin),
        .result(result),
        .cout(cout)
    );
    
    initial forever #5 clk = ~clk;
    
    initial begin
        // 初始化
        $dumpfile("wave_adder.vcd");
        $dumpvars(0, uut);
        
        d_a=0; d_b=0; cin=0; 
        en_a=0; en_b=0; en_result=0;
        rstn=0; #15; rstn=1; #10;
        
        // 测试1：完整流程
        $display("=== 测试1：完整加法流程 ===");
        // 步骤1：写入A
        d_a=100; en_a=1; #10; en_a=0;
        $display("t=%0t: 写入A=100，当前结果=%0d", $time, result);
        
        // 步骤2：写入B
        d_b=50; en_b=1; #10; en_b=0;
        $display("t=%0t: 写入B=50，当前结果=%0d", $time, result);
        
        // 步骤3：触发计算并存储结果
        en_result=1; #10; en_result=0;
        $display("t=%0t: 存储结果，result=%0d (应为150)", $time, result);
        
        // 测试2：改变A，但不更新结果
        $display("\n=== 测试2：只更新A，不更新结果 ===");
        d_a=200; en_a=1; #10; en_a=0;
        $display("t=%0t: 写入A=200，但结果仍保持=%0d", $time, result);
        
        // 测试3：再次计算
        en_result=1; #10; en_result=0;
        $display("t=%0t: 重新存储结果，result=%0d (应为250)", $time, result);
        
        // 测试4：溢出测试
        $display("\n=== 测试3：溢出测试 ===");
        d_a=65535; d_b=1; 
        en_a=1; en_b=1; #10; en_a=0; en_b=0;
        en_result=1; #10; en_result=0;
        $display("t=%0t: 65535+1=%0d cout=%0d", $time, result, cout);
        
        // 测试5：复位
        rstn=0; #10; rstn=1;
        $display("t=%0t: 复位后结果=%0d", $time, result);
        
        #20; $finish;
    end
endmodule

wave_adder.vcd
$date
	Fri Jan 09 07:40:16 2026
$end
$version
	Icarus Verilog
$end
$timescale
	1s
$end
$scope module tb_adder $end
$scope module uut $end
$var wire 1 ! cin $end
$var wire 1 " clk $end
$var wire 16 # d_a [15:0] $end
$var wire 16 $ d_b [15:0] $end
$var wire 1 % en_a $end
$var wire 1 & en_b $end
$var wire 1 ' en_result $end
$var wire 16 ( result [15:0] $end
$var wire 1 ) rstn $end
$var wire 16 * sum_wire [15:0] $end
$var wire 16 + q_result [15:0] $end
$var wire 16 , q_b [15:0] $end
$var wire 16 - q_a [15:0] $end
$var wire 1 . cout $end
$scope module adder_inst $end
$var wire 1 ! cin $end
$var wire 16 / sum [15:0] $end
$var wire 1 . cout $end
$var wire 16 0 b [15:0] $end
$var wire 16 1 a [15:0] $end
$upscope $end
$scope module register_a_inst $end
$var wire 1 " clk $end
$var wire 16 2 d [15:0] $end
$var wire 1 % en $end
$var wire 1 ) rstn $end
$var reg 16 3 q [15:0] $end
$upscope $end
$scope module register_b_inst $end
$var wire 1 " clk $end
$var wire 16 4 d [15:0] $end
$var wire 1 & en $end
$var wire 1 ) rstn $end
$var reg 16 5 q [15:0] $end
$upscope $end
$scope module result_register_inst $end
$var wire 1 " clk $end
$var wire 16 6 d [15:0] $end
$var wire 1 ' en $end
$var wire 1 ) rstn $end
$var reg 16 7 q [15:0] $end
$upscope $end
$upscope $end
$upscope $end
$enddefinitions $end
#0
$dumpvars
bx 7
bx 6
bx 5
b0 4
bx 3
b0 2
bx 1
bx 0
bx /
x.
bx -
bx ,
bx +
bx *
0)
bx (
0'
0&
0%
b0 $
b0 #
0"
0!
$end
#5
b0 *
b0 /
b0 6
0.
b0 -
b0 1
b0 3
b0 ,
b0 0
b0 5
b0 (
b0 +
b0 7
1"
#10
0"
#15
1"
1)
#20
0"
#25
b1100100 *
b1100100 /
b1100100 6
b1100100 -
b1100100 1
b1100100 3
1"
1%
b1100100 #
b1100100 2
#30
0"
#35
b10010110 *
b10010110 /
b10010110 6
b110010 ,
b110010 0
b110010 5
1"
1&
b110010 $
b110010 4
0%
#40
0"
#45
b10010110 (
b10010110 +
b10010110 7
1"
1'
0&
#50
0"
#55
b11111010 *
b11111010 /
b11111010 6
b11001000 -
b11001000 1
b11001000 3
1"
1%
b11001000 #
b11001000 2
0'
#60
0"
#65
b11111010 (
b11111010 +
b11111010 7
1"
1'
0%
#70
0"
#75
b0 *
b0 /
b0 6
1.
b1 ,
b1 0
b1 5
b1111111111111111 -
b1111111111111111 1
b1111111111111111 3
1"
1&
1%
b1 $
b1 4
b1111111111111111 #
b1111111111111111 2
0'
#80
0"
#85
b0 (
b0 +
b0 7
1"
1'
0&
0%
#90
0"
#95
0.
b0 ,
b0 0
b0 5
b0 -
b0 1
b0 3
1"
0)
0'
#100
0"
#105
1"
1)
