jiajianchengchudff.v
module subtractor_16bits(
    input [15:0] a,
    input [15:0] b,
    input bin,
    output [15:0] diff,
    output bout
);
    assign {bout, diff} = a - b - bin;
endmodule

module adder_16bits(
    input [15:0] a,
    input [15:0] b,
    input cin,
    output [15:0] sum,
    output cout
);
    assign {cout, sum} = a + b + cin;
endmodule

module multiplier_16bits(
    input [15:0] a,
    input [15:0] b,
    output [31:0] product
);
    assign product = a * b;
endmodule

module divider_16bits(
    input [15:0] dividend,
    input [15:0] divisor,
    output [15:0] quotient,
    output [15:0] remainder
);
    assign quotient = dividend / divisor;
    assign remainder = dividend % divisor;
endmodule

module dff_16bit (
    input      [15:0] d,
    input             clk,
    input             rstn,
    input             en,
    output reg [15:0] q
);
    always @(posedge clk) begin
        if (!rstn)
            q <= 16'b0;
        else if (en)
            q <= d;
    end
endmodule

system_subtractor.v
module system_subtractor (
    // 寄存器输入端口
    input      [15:0] d_a,      // 操作数A输入
    input      [15:0] d_b,      // 操作数B输入
    input             clk,
    input             rstn,
    input             en_a,      // A寄存器使能
    input             en_b,      // B寄存器使能
    input             en_result, // 结果寄存器使能
    
    // 减法器其他输入端口
    input             bin,       // 借位输入
    
    // 系统输出端口
    output     [15:0] result,    // 存储的结果输出
    output            bout       // 借位输出
);
    
    // 内部连线
    wire [15:0] q_a;      // 寄存器A输出
    wire [15:0] q_b;      // 寄存器B输出
    wire [15:0] diff_wire; // 减法器直接输出
    wire [15:0] q_result; // 结果寄存器输出
    
    // 1. 实例化第一个16位寄存器（操作数A）
    dff_16bit register_a_inst (
        .d   (d_a),
        .clk (clk),
        .rstn(rstn),
        .en  (en_a),
        .q   (q_a)
    );
    
    // 2. 实例化第二个16位寄存器（操作数B）
    dff_16bit register_b_inst (
        .d   (d_b),
        .clk (clk),
        .rstn(rstn),
        .en  (en_b),
        .q   (q_b)
    );
    
    // 3. 实例化16位减法器
    subtractor_16bits subtractor_inst (
        .a    (q_a),
        .b    (q_b),
        .bin  (bin),
        .diff (diff_wire),    // 连接到中间线
        .bout (bout)
    );
    
    // 4. 实例化16位寄存器（存储结果）
    dff_16bit result_register_inst (
        .d   (diff_wire),      
        .clk (clk),
        .rstn(rstn),
        .en  (en_result),     
        .q   (q_result)       
    );

    assign result = q_result;
    
endmodule

tb_subtractor.v
module tb_subtractor;
    reg  [15:0] d_a, d_b;
    reg clk=0, rstn, en_a, en_b, en_result, bin;
    wire [15:0] result;
    wire bout;
    
    system_subtractor uut (
        .d_a(d_a),
        .d_b(d_b),
        .clk(clk),
        .rstn(rstn),
        .en_a(en_a),
        .en_b(en_b),
        .en_result(en_result),
        .bin(bin),
        .result(result),
        .bout(bout)
    );
    
    initial forever #5 clk = ~clk;
    
    initial begin
        // 初始化
        $dumpfile("wave_subtractor.vcd");
        $dumpvars(0, uut);
        
        d_a=0; d_b=0; bin=0; 
        en_a=0; en_b=0; en_result=0;
        rstn=0; #15; rstn=1; #10;
        
        // 测试1：完整流程 - 正常减法
        $display("=== 测试1：完整减法流程 (150 - 50) ===");
        // 步骤1：写入A
        d_a=150; en_a=1; #10; en_a=0;
        $display("t=%0t: 写入A=150，当前结果=%0d", $time, result);
        
        // 步骤2：写入B
        d_b=50; en_b=1; #10; en_b=0;
        $display("t=%0t: 写入B=50，当前结果=%0d", $time, result);
        
        // 步骤3：触发计算并存储结果
        en_result=1; #10; en_result=0;
        $display("t=%0t: 存储结果，result=%0d (应为100)", $time, result);
        
        // 测试2：带借位的减法
        $display("\n=== 测试2：带借位的减法 ===");
        d_a=100; d_b=200; bin=0;
        en_a=1; en_b=1; #10; en_a=0; en_b=0;
        en_result=1; #10; en_result=0;
        $display("t=%0t: 100-200=%0d bout=%0d (借位发生)", $time, result, bout);
        
        // 测试3：更新A值并重新计算
        $display("\n=== 测试3：更新A值并重新计算 ===");
        d_a=500; en_a=1; #10; en_a=0;
        en_result=1; #10; en_result=0;
        $display("t=%0t: 500-200=%0d bout=%0d", $time, result, bout);
        
        // 测试4：带借位输入的减法
        $display("\n=== 测试4：带借位输入(bin=1)的减法 ===");
        d_a=300; d_b=200; bin=1;
        en_a=1; en_b=1; #10; en_a=0; en_b=0;
        en_result=1; #10; en_result=0;
        $display("t=%0t: 300-200-1=%0d bout=%0d", $time, result, bout);
        
        // 测试5：边界测试 - 最小值
        $display("\n=== 测试5：边界测试 (0-1) ===");
        d_a=0; d_b=1; bin=0;
        en_a=1; en_b=1; #10; en_a=0; en_b=0;
        en_result=1; #10; en_result=0;
        $display("t=%0t: 0-1=%0d bout=%0d (应为65535，借位=1)", $time, result, bout);
        
        // 测试6：测试寄存器保持功能
        $display("\n=== 测试6：测试寄存器保持功能 ===");
        // 先设置一个减法
        d_a=1000; d_b=500; bin=0;
        en_a=1; en_b=1; #10; en_a=0; en_b=0;
        en_result=1; #10; en_result=0;
        $display("t=%0t: 初始计算 1000-500=%0d", $time, result);
        
        // 只改变输入但不使能，结果应保持不变
        d_a=2000; d_b=1000; bin=0;
        #10;
        $display("t=%0t: 改变输入但不使能，结果仍为=%0d", $time, result);
        
        // 测试7：大数减小数
        $display("\n=== 测试7：大数减小数 ===");
        d_a=65535; d_b=1; bin=0;
        en_a=1; en_b=1; #10; en_a=0; en_b=0;
        en_result=1; #10; en_result=0;
        $display("t=%0t: 65535-1=%0d bout=%0d", $time, result, bout);
        
        // 测试8：复位功能测试
        $display("\n=== 测试8：复位功能测试 ===");
        // 先进行一次计算
        d_a=300; d_b=100; bin=0;
        en_a=1; en_b=1; #10; en_a=0; en_b=0;
        en_result=1; #10; en_result=0;
        $display("t=%0t: 计算300-100=%0d", $time, result);
        
        // 执行复位
        rstn=0; #10; rstn=1;
        $display("t=%0t: 复位后结果=%0d (应为0)", $time, result);
        
        // 测试9：复位后重新计算
        $display("\n=== 测试9：复位后重新计算 ===");
        d_a=12345; d_b=5432; bin=0;
        en_a=1; en_b=1; #10; en_a=0; en_b=0;
        en_result=1; #10; en_result=0;
        $display("t=%0t: 12345-5432=%0d (应为6913)", $time, result);
        
        #20; 
        $display("\n=== 所有测试完成 ===");
        $finish;
    end
    
    // 监视器，持续监测关键信号
    always @(posedge clk) begin
        if (en_a) $display("t=%0t: INFO - 写入寄存器A: %0d", $time, d_a);
        if (en_b) $display("t=%0t: INFO - 写入寄存器B: %0d", $time, d_b);
        if (en_result) $display("t=%0t: INFO - 存储结果到寄存器", $time);
        if (!rstn) $display("t=%0t: INFO - 系统复位", $time);
    end
endmodule

wave_subtractor.vcd
$date
	Fri Jan 09 07:38:30 2026
$end
$version
	Icarus Verilog
$end
$timescale
	1s
$end
$scope module tb_subtractor $end
$scope module uut $end
$var wire 1 ! bin $end
$var wire 1 " clk $end
$var wire 16 # d_a [15:0] $end
$var wire 16 $ d_b [15:0] $end
$var wire 1 % en_a $end
$var wire 1 & en_b $end
$var wire 1 ' en_result $end
$var wire 16 ( result [15:0] $end
$var wire 1 ) rstn $end
$var wire 16 * q_result [15:0] $end
$var wire 16 + q_b [15:0] $end
$var wire 16 , q_a [15:0] $end
$var wire 16 - diff_wire [15:0] $end
$var wire 1 . bout $end
$scope module register_a_inst $end
$var wire 1 " clk $end
$var wire 16 / d [15:0] $end
$var wire 1 % en $end
$var wire 1 ) rstn $end
$var reg 16 0 q [15:0] $end
$upscope $end
$scope module register_b_inst $end
$var wire 1 " clk $end
$var wire 16 1 d [15:0] $end
$var wire 1 & en $end
$var wire 1 ) rstn $end
$var reg 16 2 q [15:0] $end
$upscope $end
$scope module result_register_inst $end
$var wire 1 " clk $end
$var wire 1 ' en $end
$var wire 1 ) rstn $end
$var wire 16 3 d [15:0] $end
$var reg 16 4 q [15:0] $end
$upscope $end
$scope module subtractor_inst $end
$var wire 16 5 a [15:0] $end
$var wire 16 6 b [15:0] $end
$var wire 1 ! bin $end
$var wire 16 7 diff [15:0] $end
$var wire 1 . bout $end
$upscope $end
$upscope $end
$upscope $end
$enddefinitions $end
#0
$dumpvars
bx 7
bx 6
bx 5
bx 4
bx 3
bx 2
b0 1
bx 0
b0 /
x.
bx -
bx ,
bx +
bx *
0)
bx (
0'
0&
0%
b0 $
b0 #
0"
0!
$end
#5
b0 -
b0 3
b0 7
0.
b0 ,
b0 0
b0 5
b0 +
b0 2
b0 6
b0 (
b0 *
b0 4
1"
#10
0"
#15
1"
1)
#20
0"
#25
b10010110 -
b10010110 3
b10010110 7
b10010110 ,
b10010110 0
b10010110 5
1"
1%
b10010110 #
b10010110 /
#30
0"
#35
b1100100 -
b1100100 3
b1100100 7
b110010 +
b110010 2
b110010 6
1"
1&
b110010 $
b110010 1
0%
#40
0"
#45
b1100100 (
b1100100 *
b1100100 4
1"
1'
0&
#50
0"
#55
1.
b1111111110011100 -
b1111111110011100 3
b1111111110011100 7
b11001000 +
b11001000 2
b11001000 6
b1100100 ,
b1100100 0
b1100100 5
1"
1&
1%
b11001000 $
b11001000 1
b1100100 #
b1100100 /
0'
#60
0"
#65
b1111111110011100 (
b1111111110011100 *
b1111111110011100 4
1"
1'
0&
0%
#70
0"
#75
b100101100 -
b100101100 3
b100101100 7
0.
b111110100 ,
b111110100 0
b111110100 5
1"
1%
b111110100 #
b111110100 /
0'
#80
0"
#85
b100101100 (
b100101100 *
b100101100 4
1"
1'
0%
#90
0"
#95
b100101100 ,
b100101100 0
b100101100 5
b1100011 -
b1100011 3
b1100011 7
1"
1&
1%
1!
b100101100 #
b100101100 /
0'
#100
0"
#105
b1100011 (
b1100011 *
b1100011 4
1"
1'
0&
0%
#110
0"
#115
1.
b1 +
b1 2
b1 6
b0 ,
b0 0
b0 5
b1111111111111111 -
b1111111111111111 3
b1111111111111111 7
1"
1&
1%
0!
b1 $
b1 1
b0 #
b0 /
0'
#120
0"
#125
b1111111111111111 (
b1111111111111111 *
b1111111111111111 4
1"
1'
0&
0%
#130
0"
#135
b111110100 -
b111110100 3
b111110100 7
0.
b111110100 +
b111110100 2
b111110100 6
b1111101000 ,
b1111101000 0
b1111101000 5
1"
1&
1%
b111110100 $
b111110100 1
b1111101000 #
b1111101000 /
0'
#140
0"
#145
b111110100 (
b111110100 *
b111110100 4
1"
1'
0&
0%
#150
0"
#155
1"
b1111101000 $
b1111101000 1
b11111010000 #
b11111010000 /
0'
#160
0"
#165
b1111111111111110 -
b1111111111111110 3
b1111111111111110 7
b1111111111111111 ,
b1111111111111111 0
b1111111111111111 5
b1 +
b1 2
b1 6
1"
1&
1%
b1 $
b1 1
b1111111111111111 #
b1111111111111111 /
#170
0"
#175
b1111111111111110 (
b1111111111111110 *
b1111111111111110 4
1"
1'
0&
0%
#180
0"
#185
b11001000 -
b11001000 3
b11001000 7
b100101100 ,
b100101100 0
b100101100 5
b1100100 +
b1100100 2
b1100100 6
1"
1&
1%
b1100100 $
b1100100 1
b100101100 #
b100101100 /
0'
#190
0"
#195
b11001000 (
b11001000 *
b11001000 4
1"
1'
0&
0%
#200
0"
#205
b0 -
b0 3
b0 7
b0 ,
b0 0
b0 5
b0 +
b0 2
b0 6
b0 (
b0 *
b0 4
1"
0)
0'
#210
0"
#215
b1101100000001 -
b1101100000001 3
b1101100000001 7
b1010100111000 +
b1010100111000 2
b1010100111000 6
b11000000111001 ,
b11000000111001 0
b11000000111001 5
1"
1&
1%
b1010100111000 $
b1010100111000 1
b11000000111001 #
b11000000111001 /
1)
#220
0"
#225
b1101100000001 (
b1101100000001 *
b1101100000001 4
1"
1'
0&
0%
#230
0"
#235
1"
0'
