jiajianchengchudff.v
module subtractor_16bits(
    input [15:0] a,
    input [15:0] b,
    input bin,
    output [15:0] diff,
    output bout
);
    assign {bout, diff} = a - b - bin;
endmodule

module adder_16bits(
    input [15:0] a,
    input [15:0] b,
    input cin,
    output [15:0] sum,
    output cout
);
    assign {cout, sum} = a + b + cin;
endmodule

module multiplier_16bits(
    input [15:0] a,
    input [15:0] b,
    output [31:0] product
);
    assign product = a * b;
endmodule

module divider_16bits(
    input [15:0] dividend,
    input [15:0] divisor,
    output [15:0] quotient,
    output [15:0] remainder
);
    assign quotient = dividend / divisor;
    assign remainder = dividend % divisor;
endmodule

module dff_16bit (
    input      [15:0] d,
    input             clk,
    input             rstn,
    input             en,
    output reg [15:0] q
);
    always @(posedge clk) begin
        if (!rstn)
            q <= 16'b0;
        else if (en)
            q <= d;
    end
endmodule

system_divider.v
module system_divider (
    // 寄存器输入端口
    input      [15:0] d_a,         // 被除数输入
    input      [15:0] d_b,         // 除数输入
    input             clk,
    input             rstn,
    input             en_a,         // 被除数寄存器使能
    input             en_b,         // 除数寄存器使能
    input             en_result,    // 结果寄存器使能
    
    // 系统输出端口
    output     [15:0] quotient,     // 商输出
    output     [15:0] remainder     // 余数输出
);
    
    // 内部连线
    wire [15:0] q_a;               // 被除数寄存器输出
    wire [15:0] q_b;               // 除数寄存器输出
    wire [15:0] quotient_wire;     // 除法器商输出
    wire [15:0] remainder_wire;    // 除法器余数输出
    reg  [15:0] quotient_reg;      // 商寄存器
    reg  [15:0] remainder_reg;     // 余数寄存器
    
    // 1. 实例化第一个16位寄存器（被除数）
    dff_16bit dividend_register_inst (
        .d   (d_a),
        .clk (clk),
        .rstn(rstn),
        .en  (en_a),
        .q   (q_a)
    );
    
    // 2. 实例化第二个16位寄存器（除数）
    dff_16bit divisor_register_inst (
        .d   (d_b),
        .clk (clk),
        .rstn(rstn),
        .en  (en_b),
        .q   (q_b)
    );
    
    // 3. 实例化16位除法器
    divider_16bits divider_inst (
        .dividend (q_a),
        .divisor  (q_b),
        .quotient (quotient_wire),
        .remainder(remainder_wire)
    );
    
    // 4. 结果寄存器（商和余数）
    always @(posedge clk) begin
        if (!rstn) begin
            quotient_reg  <= 16'b0;
            remainder_reg <= 16'b0;
        end
        else if (en_result) begin
            quotient_reg  <= quotient_wire;
            remainder_reg <= remainder_wire;
        end
    end

    assign quotient  = quotient_reg;
    assign remainder = remainder_reg;
    
endmodule

tb_divider.v
module tb_divider;
    reg  [15:0] d_a, d_b;
    reg clk=0, rstn, en_a, en_b, en_result;
    wire [15:0] quotient, remainder;
    
    system_divider uut (
        .d_a(d_a),
        .d_b(d_b),
        .clk(clk),
        .rstn(rstn),
        .en_a(en_a),
        .en_b(en_b),
        .en_result(en_result),
        .quotient(quotient),
        .remainder(remainder)
    );
    
    // 时钟生成
    initial forever #5 clk = ~clk;
    
    initial begin
        // 初始化
        $dumpfile("wave_divider.vcd");
        $dumpvars(0, uut);
        
        d_a = 0; 
        d_b = 0;
        en_a = 0; 
        en_b = 0; 
        en_result = 0;
        rstn = 0; 
        #15; 
        rstn = 1; 
        #10;
        
        // 测试1：完整除法流程 - 整除情况
        $display("=== 测试1：完整除法流程 (100 ÷ 50) ===");
        // 步骤1：写入被除数
        d_a = 100; 
        en_a = 1; 
        #10; 
        en_a = 0;
        $display("t=%0t: 写入被除数=100，当前商=%0d，余数=%0d", 
                 $time, quotient, remainder);
        
        // 步骤2：写入除数
        d_b = 50; 
        en_b = 1; 
        #10; 
        en_b = 0;
        $display("t=%0t: 写入除数=50，当前商=%0d，余数=%0d", 
                 $time, quotient, remainder);
        
        // 步骤3：触发计算并存储结果
        en_result = 1; 
        #10; 
        en_result = 0;
        $display("t=%0t: 存储结果，商=%0d，余数=%0d (应为商=2，余数=0)", 
                 $time, quotient, remainder);
        
        // 测试2：有余数的除法
        $display("\n=== 测试2：有余数的除法 (17 ÷ 5) ===");
        d_a = 17; 
        d_b = 5;
        en_a = 1; 
        en_b = 1; 
        #10; 
        en_a = 0; 
        en_b = 0;
        en_result = 1; 
        #10; 
        en_result = 0;
        $display("t=%0t: 17÷5=商%0d，余数%0d (应为商=3，余数=2)", 
                 $time, quotient, remainder);
        
        // 测试3：改变被除数，但不更新结果
        $display("\n=== 测试3：只更新被除数，不更新结果 ===");
        d_a = 200; 
        en_a = 1; 
        #10; 
        en_a = 0;
        $display("t=%0t: 写入被除数=200，但结果仍保持：商=%0d，余数=%0d", 
                 $time, quotient, remainder);
        
        // 测试4：再次计算
        en_result = 1; 
        #10; 
        en_result = 0;
        $display("t=%0t: 重新存储结果，商=%0d，余数=%0d (应为200÷5=40余0)", 
                 $time, quotient, remainder);
        
        // 测试5：除数为1的情况
        $display("\n=== 测试5：除数为1的除法 ===");
        d_a = 12345; 
        d_b = 1;
        en_a = 1; 
        en_b = 1; 
        #10; 
        en_a = 0; 
        en_b = 0;
        en_result = 1; 
        #10; 
        en_result = 0;
        $display("t=%0t: 12345÷1=商%0d，余数%0d (应为商=12345，余数=0)", 
                 $time, quotient, remainder);
        
        // 测试6：被除数小于除数
        $display("\n=== 测试6：被除数小于除数 (5 ÷ 10) ===");
        d_a = 5; 
        d_b = 10;
        en_a = 1; 
        en_b = 1; 
        #10; 
        en_a = 0; 
        en_b = 0;
        en_result = 1; 
        #10; 
        en_result = 0;
        $display("t=%0t: 5÷10=商%0d，余数%0d (应为商=0，余数=5)", 
                 $time, quotient, remainder);
        
        // 测试7：除数为0的情况（注意：整数除法中除以0的行为）
        $display("\n=== 测试7：除数为0的情况 (100 ÷ 0) ===");
        d_a = 100; 
        d_b = 0;
        en_a = 1; 
        en_b = 1; 
        #10; 
        en_a = 0; 
        en_b = 0;
        en_result = 1; 
        #10; 
        en_result = 0;
        $display("t=%0t: 100÷0=商%0d，余数%0d (注意：Verilog中除以0的结果)", 
                 $time, quotient, remainder);
        
        // 测试8：最大值除法
        $display("\n=== 测试8：最大值除法 ===");
        d_a = 65535; 
        d_b = 65535;
        en_a = 1; 
        en_b = 1; 
        #10; 
        en_a = 0; 
        en_b = 0;
        en_result = 1; 
        #10; 
        en_result = 0;
        $display("t=%0t: 65535÷65535=商%0d，余数%0d (应为商=1，余数=0)", 
                 $time, quotient, remainder);
        
        // 测试9：大数除法
        $display("\n=== 测试9：大数除法 (65535 ÷ 256) ===");
        d_a = 65535; 
        d_b = 256;
        en_a = 1; 
        en_b = 1; 
        #10; 
        en_a = 0; 
        en_b = 0;
        en_result = 1; 
        #10; 
        en_result = 0;
        $display("t=%0t: 65535÷256=商%0d，余数%0d (应为商=255，余数=255)", 
                 $time, quotient, remainder);
        
        // 测试10：精确除法
        $display("\n=== 测试10：精确除法 (1000 ÷ 8) ===");
        d_a = 1000; 
        d_b = 8;
        en_a = 1; 
        en_b = 1; 
        #10; 
        en_a = 0; 
        en_b = 0;
        en_result = 1; 
        #10; 
        en_result = 0;
        $display("t=%0t: 1000÷8=商%0d，余数%0d (应为商=125，余数=0)", 
                 $time, quotient, remainder);
        
        // 测试11：测试寄存器保持功能
        $display("\n=== 测试11：测试寄存器保持功能 ===");
        // 先进行一次计算
        d_a = 99; 
        d_b = 4;
        en_a = 1; 
        en_b = 1; 
        #10; 
        en_a = 0; 
        en_b = 0;
        en_result = 1; 
        #10; 
        en_result = 0;
        $display("t=%0t: 初始计算 99÷4=商%0d，余数%0d", 
                 $time, quotient, remainder);
        
        // 只改变输入但不使能，结果应保持不变
        d_a = 888; 
        d_b = 7;
        #10;
        $display("t=%0t: 改变输入但不使能，结果仍保持：商=%0d，余数=%0d", 
                 $time, quotient, remainder);
        
        // 测试12：复杂余数测试
        $display("\n=== 测试12：复杂余数测试 ===");
        d_a = 12345; 
        d_b = 67;
        en_a = 1; 
        en_b = 1; 
        #10; 
        en_a = 0; 
        en_b = 0;
        en_result = 1; 
        #10; 
        en_result = 0;
        $display("t=%0t: 12345÷67=商%0d，余数%0d (验证: 67×184+17=12345)", 
                 $time, quotient, remainder);
        
        // 测试13：连续除法运算
        $display("\n=== 测试13：连续除法运算 ===");
        // 第一次除法
        d_a = 100; 
        d_b = 3;
        en_a = 1; 
        en_b = 1; 
        #10; 
        en_a = 0; 
        en_b = 0;
        en_result = 1; 
        #10; 
        en_result = 0;
        $display("t=%0t: 第一次: 100÷3=商%0d，余数%0d", 
                 $time, quotient, remainder);
        
        // 第二次除法（只改变被除数）
        d_a = 200;
        en_a = 1; 
        #10; 
        en_a = 0;
        en_result = 1; 
        #10; 
        en_result = 0;
        $display("t=%0t: 第二次: 200÷3=商%0d，余数%0d", 
                 $time, quotient, remainder);
        
        // 第三次除法（改变除数）
        d_b = 15;
        en_b = 1; 
        #10; 
        en_b = 0;
        en_result = 1; 
        #10; 
        en_result = 0;
        $display("t=%0t: 第三次: 200÷15=商%0d，余数%0d", 
                 $time, quotient, remainder);
        
        // 测试14：复位功能测试
        $display("\n=== 测试14：复位功能测试 ===");
        // 先进行一次计算
        d_a = 789; 
        d_b = 12;
        en_a = 1; 
        en_b = 1; 
        #10; 
        en_a = 0; 
        en_b = 0;
        en_result = 1; 
        #10; 
        en_result = 0;
        $display("t=%0t: 计算789÷12=商%0d，余数%0d", 
                 $time, quotient, remainder);
        
        // 执行复位
        rstn = 0; 
        #10; 
        rstn = 1;
        $display("t=%0t: 复位后：商=%0d，余数=%0d (应为0, 0)", 
                 $time, quotient, remainder);
        
        // 测试15：复位后重新计算
        $display("\n=== 测试15：复位后重新计算 ===");
        d_a = 54321; 
        d_b = 123;
        en_a = 1; 
        en_b = 1; 
        #10; 
        en_a = 0; 
        en_b = 0;
        en_result = 1; 
        #10; 
        en_result = 0;
        $display("t=%0t: 54321÷123=商%0d，余数%0d (应为商=441，余数=78)", 
                 $time, quotient, remainder);
        
        // 测试16：边界值测试 - 最小非零值
        $display("\n=== 测试16：边界值测试 ===");
        d_a = 1; 
        d_b = 1;
        en_a = 1; 
        en_b = 1; 
        #10; 
        en_a = 0; 
        en_b = 0;
        en_result = 1; 
        #10; 
        en_result = 0;
        $display("t=%0t: 1÷1=商%0d，余数%0d", 
                 $time, quotient, remainder);
        
        d_a = 65535; 
        d_b = 2;
        en_a = 1; 
        en_b = 1; 
        #10; 
        en_a = 0; 
        en_b = 0;
        en_result = 1; 
        #10; 
        en_result = 0;
        $display("t=%0t: 65535÷2=商%0d，余数%0d (应为商=32767，余数=1)", 
                 $time, quotient, remainder);
        
        #20; 
        $display("\n=== 所有除法测试完成 ===");
        $display("=== 测试总结 ===");
        $display("1. 正常除法测试 ✓");
        $display("2. 余数测试 ✓");
        $display("3. 边界条件测试 ✓");
        $display("4. 寄存器保持功能 ✓");
        $display("5. 复位功能 ✓");
        $display("6. 连续运算测试 ✓");
        $finish;
    end
    
    // 监视器，持续监测关键信号
    always @(posedge clk) begin
        if (en_a) $display("t=%0t: INFO - 写入被除数寄存器: %0d", $time, d_a);
        if (en_b) $display("t=%0t: INFO - 写入除数寄存器: %0d", $time, d_b);
        if (en_result) $display("t=%0t: INFO - 存储除法结果到寄存器", $time);
        if (!rstn) $display("t=%0t: INFO - 系统复位", $time);
    end
endmodule

wave_divider.vcd
$date
	Fri Jan 09 08:13:05 2026
$end
$version
	Icarus Verilog
$end
$timescale
	1s
$end
$scope module tb_divider $end
$scope module uut $end
$var wire 1 ! clk $end
$var wire 16 " d_a [15:0] $end
$var wire 16 # d_b [15:0] $end
$var wire 1 $ en_a $end
$var wire 1 % en_b $end
$var wire 1 & en_result $end
$var wire 16 ' quotient [15:0] $end
$var wire 16 ( remainder [15:0] $end
$var wire 1 ) rstn $end
$var wire 16 * remainder_wire [15:0] $end
$var wire 16 + quotient_wire [15:0] $end
$var wire 16 , q_b [15:0] $end
$var wire 16 - q_a [15:0] $end
$var reg 16 . quotient_reg [15:0] $end
$var reg 16 / remainder_reg [15:0] $end
$scope module dividend_register_inst $end
$var wire 1 ! clk $end
$var wire 16 0 d [15:0] $end
$var wire 1 $ en $end
$var wire 1 ) rstn $end
$var reg 16 1 q [15:0] $end
$upscope $end
$scope module divider_inst $end
$var wire 16 2 dividend [15:0] $end
$var wire 16 3 remainder [15:0] $end
$var wire 16 4 quotient [15:0] $end
$var wire 16 5 divisor [15:0] $end
$upscope $end
$scope module divisor_register_inst $end
$var wire 1 ! clk $end
$var wire 16 6 d [15:0] $end
$var wire 1 % en $end
$var wire 1 ) rstn $end
$var reg 16 7 q [15:0] $end
$upscope $end
$upscope $end
$upscope $end
$enddefinitions $end
#0
$dumpvars
bx 7
b0 6
bx 5
bx 4
bx 3
bx 2
bx 1
b0 0
bx /
bx .
bx -
bx ,
bx +
bx *
0)
bx (
bx '
0&
0%
0$
b0 #
b0 "
0!
$end
#5
b0 -
b0 1
b0 2
b0 ,
b0 5
b0 7
b0 (
b0 /
b0 '
b0 .
1!
#10
0!
#15
1!
1)
#20
0!
#25
b1100100 -
b1100100 1
b1100100 2
1!
1$
b1100100 "
b1100100 0
#30
0!
#35
b0 *
b0 3
b10 +
b10 4
b110010 ,
b110010 5
b110010 7
1!
1%
b110010 #
b110010 6
0$
#40
0!
#45
b10 '
b10 .
1!
1&
0%
#50
0!
#55
b101 ,
b101 5
b101 7
b11 +
b11 4
b10 *
b10 3
b10001 -
b10001 1
b10001 2
1!
1%
1$
b101 #
b101 6
b10001 "
b10001 0
0&
#60
0!
#65
b10 (
b10 /
b11 '
b11 .
1!
1&
0%
0$
#70
0!
#75
b101000 +
b101000 4
b0 *
b0 3
b11001000 -
b11001000 1
b11001000 2
1!
1$
b11001000 "
b11001000 0
0&
#80
0!
#85
b0 (
b0 /
b101000 '
b101000 .
1!
1&
0$
#90
0!
#95
b1 ,
b1 5
b1 7
b11000000111001 +
b11000000111001 4
b11000000111001 -
b11000000111001 1
b11000000111001 2
1!
1%
1$
b1 #
b1 6
b11000000111001 "
b11000000111001 0
0&
#100
0!
#105
b11000000111001 '
b11000000111001 .
1!
1&
0%
0$
#110
0!
#115
b101 *
b101 3
b1010 ,
b1010 5
b1010 7
b0 +
b0 4
b101 -
b101 1
b101 2
1!
1%
1$
b1010 #
b1010 6
b101 "
b101 0
0&
#120
0!
#125
b101 (
b101 /
b0 '
b0 .
1!
1&
0%
0$
#130
0!
#135
b0 ,
b0 5
b0 7
bx +
bx 4
bx *
bx 3
b1100100 -
b1100100 1
b1100100 2
1!
1%
1$
b0 #
b0 6
b1100100 "
b1100100 0
0&
#140
0!
#145
bx (
bx /
bx '
bx .
1!
1&
0%
0$
#150
0!
#155
b0 *
b0 3
b1 +
b1 4
b1111111111111111 ,
b1111111111111111 5
b1111111111111111 7
b1111111111111111 -
b1111111111111111 1
b1111111111111111 2
1!
1%
1$
b1111111111111111 #
b1111111111111111 6
b1111111111111111 "
b1111111111111111 0
0&
#160
0!
#165
b0 (
b0 /
b1 '
b1 .
1!
1&
0%
0$
#170
0!
#175
b11111111 *
b11111111 3
b11111111 +
b11111111 4
b100000000 ,
b100000000 5
b100000000 7
1!
1%
1$
b100000000 #
b100000000 6
0&
#180
0!
#185
b11111111 (
b11111111 /
b11111111 '
b11111111 .
1!
1&
0%
0$
#190
0!
#195
b1000 ,
b1000 5
b1000 7
b1111101 +
b1111101 4
b0 *
b0 3
b1111101000 -
b1111101000 1
b1111101000 2
1!
1%
1$
b1000 #
b1000 6
b1111101000 "
b1111101000 0
0&
#200
0!
#205
b0 (
b0 /
b1111101 '
b1111101 .
1!
1&
0%
0$
#210
0!
#215
b100 ,
b100 5
b100 7
b11000 +
b11000 4
b11 *
b11 3
b1100011 -
b1100011 1
b1100011 2
1!
1%
1$
b100 #
b100 6
b1100011 "
b1100011 0
0&
#220
0!
#225
b11 (
b11 /
b11000 '
b11000 .
1!
1&
0%
0$
#230
0!
#235
1!
b111 #
b111 6
b1101111000 "
b1101111000 0
0&
#240
0!
#245
b11000000111001 -
b11000000111001 1
b11000000111001 2
b10001 *
b10001 3
b10111000 +
b10111000 4
b1000011 ,
b1000011 5
b1000011 7
1!
1%
1$
b1000011 #
b1000011 6
b11000000111001 "
b11000000111001 0
#250
0!
#255
b10001 (
b10001 /
b10111000 '
b10111000 .
1!
1&
0%
0$
#260
0!
#265
b1100100 -
b1100100 1
b1100100 2
b1 *
b1 3
b100001 +
b100001 4
b11 ,
b11 5
b11 7
1!
1%
1$
b11 #
b11 6
b1100100 "
b1100100 0
0&
#270
0!
#275
b1 (
b1 /
b100001 '
b100001 .
1!
1&
0%
0$
#280
0!
#285
b1000010 +
b1000010 4
b10 *
b10 3
b11001000 -
b11001000 1
b11001000 2
1!
1$
b11001000 "
b11001000 0
0&
#290
0!
#295
b10 (
b10 /
b1000010 '
b1000010 .
1!
1&
0$
#300
0!
#305
b101 *
b101 3
b1101 +
b1101 4
b1111 ,
b1111 5
b1111 7
1!
1%
b1111 #
b1111 6
0&
#310
0!
#315
b101 (
b101 /
b1101 '
b1101 .
1!
1&
0%
#320
0!
#325
b1100010101 -
b1100010101 1
b1100010101 2
b1001 *
b1001 3
b1000001 +
b1000001 4
b1100 ,
b1100 5
b1100 7
1!
1%
1$
b1100 #
b1100 6
b1100010101 "
b1100010101 0
0&
#330
0!
#335
b1001 (
b1001 /
b1000001 '
b1000001 .
1!
1&
0%
0$
#340
0!
#345
b0 -
b0 1
b0 2
bx *
bx 3
bx +
bx 4
b0 ,
b0 5
b0 7
b0 (
b0 /
b0 '
b0 .
1!
0)
0&
#350
0!
#355
b1001110 *
b1001110 3
b110111001 +
b110111001 4
b1111011 ,
b1111011 5
b1111011 7
b1101010000110001 -
b1101010000110001 1
b1101010000110001 2
1!
1%
1$
b1111011 #
b1111011 6
b1101010000110001 "
b1101010000110001 0
1)
#360
0!
#365
b1001110 (
b1001110 /
b110111001 '
b110111001 .
1!
1&
0%
0$
#370
0!
#375
b1 ,
b1 5
b1 7
b1 +
b1 4
b0 *
b0 3
b1 -
b1 1
b1 2
1!
1%
1$
b1 #
b1 6
b1 "
b1 0
0&
#380
0!
#385
b0 (
b0 /
b1 '
b1 .
1!
1&
0%
0$
#390
0!
#395
b1 *
b1 3
b10 ,
b10 5
b10 7
b111111111111111 +
b111111111111111 4
b1111111111111111 -
b1111111111111111 1
b1111111111111111 2
1!
1%
1$
b10 #
b10 6
b1111111111111111 "
b1111111111111111 0
0&
#400
0!
#405
b1 (
b1 /
b111111111111111 '
b111111111111111 .
1!
1&
0%
0$
#410
0!
#415
1!
0&
