jiajianchengchudff.v
module subtractor_16bits(
    input [15:0] a,
    input [15:0] b,
    input bin,
    output [15:0] diff,
    output bout
);
    assign {bout, diff} = a - b - bin;
endmodule

module adder_16bits(
    input [15:0] a,
    input [15:0] b,
    input cin,
    output [15:0] sum,
    output cout
);
    assign {cout, sum} = a + b + cin;
endmodule

module multiplier_16bits(
    input [15:0] a,
    input [15:0] b,
    output [31:0] product
);
    assign product = a * b;
endmodule

module divider_16bits(
    input [15:0] dividend,
    input [15:0] divisor,
    output [15:0] quotient,
    output [15:0] remainder
);
    assign quotient = dividend / divisor;
    assign remainder = dividend % divisor;
endmodule

module dff_16bit (
    input      [15:0] d,
    input             clk,
    input             rstn,
    input             en,
    output reg [15:0] q
);
    always @(posedge clk) begin
        if (!rstn)
            q <= 16'b0;
        else if (en)
            q <= d;
    end
endmodule

system_multiplier.v
module system_multiplier (
    // 寄存器输入端口
    input      [15:0] d_a,      // 操作数A输入
    input      [15:0] d_b,      // 操作数B输入
    input             clk,
    input             rstn,
    input             en_a,      // A寄存器使能
    input             en_b,      // B寄存器使能
    input             en_result, // 结果寄存器使能
    
    // 系统输出端口
    output     [31:0] result     // 32位乘法结果输出
);
    
    // 内部连线
    wire [15:0] q_a;          // 寄存器A输出
    wire [15:0] q_b;          // 寄存器B输出
    wire [31:0] product_wire; // 乘法器直接输出
    wire [31:0] q_result;     // 结果寄存器输出
    
    // 1. 实例化第一个16位寄存器（操作数A）
    dff_16bit register_a_inst (
        .d   (d_a),
        .clk (clk),
        .rstn(rstn),
        .en  (en_a),
        .q   (q_a)
    );
    
    // 2. 实例化第二个16位寄存器（操作数B）
    dff_16bit register_b_inst (
        .d   (d_b),
        .clk (clk),
        .rstn(rstn),
        .en  (en_b),
        .q   (q_b)
    );
    
    // 3. 实例化16位乘法器
    multiplier_16bits multiplier_inst (
        .a      (q_a),
        .b      (q_b),
        .product(product_wire)
    );
    
    // 4. 实例化32位结果寄存器（存储结果）
    // 注意：这里需要使用32位寄存器，所以我们创建一个临时的32位寄存器
    // 由于dff_16bit是16位，我们需要32位版本
    reg [31:0] result_reg;
    
    always @(posedge clk) begin
        if (!rstn)
            result_reg <= 32'b0;
        else if (en_result)
            result_reg <= product_wire;
    end

    assign result = result_reg;
    
endmodule

tb_multiplier.v
module tb_multiplier;
    reg  [15:0] d_a, d_b;
    reg clk=0, rstn, en_a, en_b, en_result;
    wire [31:0] result;
    
    system_multiplier uut (
        .d_a(d_a),
        .d_b(d_b),
        .clk(clk),
        .rstn(rstn),
        .en_a(en_a),
        .en_b(en_b),
        .en_result(en_result),
        .result(result)
    );
    
    // 时钟生成
    initial forever #5 clk = ~clk;
    
    initial begin
        // 初始化
        $dumpfile("wave_multiplier.vcd");
        $dumpvars(0, uut);
        
        d_a = 0; 
        d_b = 0;
        en_a = 0; 
        en_b = 0; 
        en_result = 0;
        rstn = 0; 
        #15; 
        rstn = 1; 
        #10;
        
        // 测试1：完整乘法流程 - 小数字
        $display("=== 测试1：完整乘法流程 (100 × 50) ===");
        // 步骤1：写入A
        d_a = 100; 
        en_a = 1; 
        #10; 
        en_a = 0;
        $display("t=%0t: 写入A=100，当前结果=%0d", $time, result);
        
        // 步骤2：写入B
        d_b = 50; 
        en_b = 1; 
        #10; 
        en_b = 0;
        $display("t=%0t: 写入B=50，当前结果=%0d", $time, result);
        
        // 步骤3：触发计算并存储结果
        en_result = 1; 
        #10; 
        en_result = 0;
        $display("t=%0t: 存储结果，result=%0d (应为5000)", $time, result);
        
        // 测试2：改变A，但不更新结果
        $display("\n=== 测试2：只更新A，不更新结果 ===");
        d_a = 200; 
        en_a = 1; 
        #10; 
        en_a = 0;
        $display("t=%0t: 写入A=200，但结果仍保持=%0d", $time, result);
        
        // 测试3：再次计算
        en_result = 1; 
        #10; 
        en_result = 0;
        $display("t=%0t: 重新存储结果，result=%0d (应为10000)", $time, result);
        
        // 测试4：大数乘法
        $display("\n=== 测试3：大数乘法测试 ===");
        d_a = 255; 
        d_b = 255;
        en_a = 1; 
        en_b = 1; 
        #10; 
        en_a = 0; 
        en_b = 0;
        en_result = 1; 
        #10; 
        en_result = 0;
        $display("t=%0t: 255×255=%0d (应为65025)", $time, result);
        
        // 测试5：最大值乘法
        $display("\n=== 测试4：最大值乘法测试 ===");
        d_a = 65535; 
        d_b = 1;
        en_a = 1; 
        en_b = 1; 
        #10; 
        en_a = 0; 
        en_b = 0;
        en_result = 1; 
        #10; 
        en_result = 0;
        $display("t=%0t: 65535×1=%0d", $time, result);
        
        // 测试6：中等大小数乘法
        $display("\n=== 测试5：中等大小数乘法 ===");
        d_a = 1234; 
        d_b = 567;
        en_a = 1; 
        en_b = 1; 
        #10; 
        en_a = 0; 
        en_b = 0;
        en_result = 1; 
        #10; 
        en_result = 0;
        $display("t=%0t: 1234×567=%0d (应为699,678)", $time, result);
        
        // 测试7：测试寄存器保持功能
        $display("\n=== 测试6：测试寄存器保持功能 ===");
        // 先设置一个乘法
        d_a = 100; 
        d_b = 10;
        en_a = 1; 
        en_b = 1; 
        #10; 
        en_a = 0; 
        en_b = 0;
        en_result = 1; 
        #10; 
        en_result = 0;
        $display("t=%0t: 初始计算 100×10=%0d", $time, result);
        
        // 只改变输入但不使能，结果应保持不变
        d_a = 2000; 
        d_b = 3000;
        #10;
        $display("t=%0t: 改变输入但不使能，结果仍为=%0d", $time, result);
        
        // 测试8：乘0测试
        $display("\n=== 测试7：乘0测试 ===");
        d_a = 12345; 
        d_b = 0;
        en_a = 1; 
        en_b = 1; 
        #10; 
        en_a = 0; 
        en_b = 0;
        en_result = 1; 
        #10; 
        en_result = 0;
        $display("t=%0t: 12345×0=%0d (应为0)", $time, result);
        
        // 测试9：对称乘法
        $display("\n=== 测试8：对称乘法测试 ===");
        d_a = 77; 
        d_b = 88;
        en_a = 1; 
        en_b = 1; 
        #10; 
        en_a = 0; 
        en_b = 0;
        en_result = 1; 
        #10; 
        en_result = 0;
        $display("t=%0t: 77×88=%0d (应为6776)", $time, result);
        
        // 验证交换律
        d_a = 88; 
        d_b = 77;
        en_a = 1; 
        en_b = 1; 
        #10; 
        en_a = 0; 
        en_b = 0;
        en_result = 1; 
        #10; 
        en_result = 0;
        $display("t=%0t: 88×77=%0d (也应为6776)", $time, result);
        
        // 测试10：复位功能测试
        $display("\n=== 测试9：复位功能测试 ===");
        // 先进行一次计算
        d_a = 300; 
        d_b = 100;
        en_a = 1; 
        en_b = 1; 
        #10; 
        en_a = 0; 
        en_b = 0;
        en_result = 1; 
        #10; 
        en_result = 0;
        $display("t=%0t: 计算300×100=%0d", $time, result);
        
        // 执行复位
        rstn = 0; 
        #10; 
        rstn = 1;
        $display("t=%0t: 复位后结果=%0d (应为0)", $time, result);
        
        // 测试11：复位后重新计算
        $display("\n=== 测试10：复位后重新计算 ===");
        d_a = 123; 
        d_b = 456;
        en_a = 1; 
        en_b = 1; 
        #10; 
        en_a = 0; 
        en_b = 0;
        en_result = 1; 
        #10; 
        en_result = 0;
        $display("t=%0t: 123×456=%0d (应为56088)", $time, result);
        
        // 测试12：边界值测试
        $display("\n=== 测试11：边界值测试 ===");
        d_a = 1; 
        d_b = 65535;
        en_a = 1; 
        en_b = 1; 
        #10; 
        en_a = 0; 
        en_b = 0;
        en_result = 1; 
        #10; 
        en_result = 0;
        $display("t=%0t: 1×65535=%0d", $time, result);
        
        d_a = 32767; 
        d_b = 2;
        en_a = 1; 
        en_b = 1; 
        #10; 
        en_a = 0; 
        en_b = 0;
        en_result = 1; 
        #10; 
        en_result = 0;
        $display("t=%0t: 32767×2=%0d (应为65534)", $time, result);
        
        #20; 
        $display("\n=== 所有乘法测试完成 ===");
        $finish;
    end
    
    // 监视器，持续监测关键信号
    always @(posedge clk) begin
        if (en_a) $display("t=%0t: INFO - 写入寄存器A: %0d", $time, d_a);
        if (en_b) $display("t=%0t: INFO - 写入寄存器B: %0d", $time, d_b);
        if (en_result) $display("t=%0t: INFO - 存储乘法结果到寄存器", $time);
        if (!rstn) $display("t=%0t: INFO - 系统复位", $time);
    end
endmodule

wave_multiplier.vcd
$date
	Fri Jan 09 08:07:46 2026
$end
$version
	Icarus Verilog
$end
$timescale
	1s
$end
$scope module tb_multiplier $end
$scope module uut $end
$var wire 1 ! clk $end
$var wire 16 " d_a [15:0] $end
$var wire 16 # d_b [15:0] $end
$var wire 1 $ en_a $end
$var wire 1 % en_b $end
$var wire 1 & en_result $end
$var wire 32 ' result [31:0] $end
$var wire 1 ( rstn $end
$var wire 16 ) q_b [15:0] $end
$var wire 16 * q_a [15:0] $end
$var wire 32 + product_wire [31:0] $end
$var reg 32 , result_reg [31:0] $end
$scope module multiplier_inst $end
$var wire 32 - product [31:0] $end
$var wire 16 . b [15:0] $end
$var wire 16 / a [15:0] $end
$upscope $end
$scope module register_a_inst $end
$var wire 1 ! clk $end
$var wire 16 0 d [15:0] $end
$var wire 1 $ en $end
$var wire 1 ( rstn $end
$var reg 16 1 q [15:0] $end
$upscope $end
$scope module register_b_inst $end
$var wire 1 ! clk $end
$var wire 16 2 d [15:0] $end
$var wire 1 % en $end
$var wire 1 ( rstn $end
$var reg 16 3 q [15:0] $end
$upscope $end
$upscope $end
$upscope $end
$enddefinitions $end
#0
$dumpvars
bx 3
b0 2
bx 1
b0 0
bx /
bx .
bx -
bx ,
bx +
bx *
bx )
0(
bx '
0&
0%
0$
b0 #
b0 "
0!
$end
#5
b0 +
b0 -
b0 *
b0 /
b0 1
b0 )
b0 .
b0 3
b0 '
b0 ,
1!
#10
0!
#15
1!
1(
#20
0!
#25
b1100100 *
b1100100 /
b1100100 1
1!
1$
b1100100 "
b1100100 0
#30
0!
#35
b1001110001000 +
b1001110001000 -
b110010 )
b110010 .
b110010 3
1!
1%
b110010 #
b110010 2
0$
#40
0!
#45
b1001110001000 '
b1001110001000 ,
1!
1&
0%
#50
0!
#55
b10011100010000 +
b10011100010000 -
b11001000 *
b11001000 /
b11001000 1
1!
1$
b11001000 "
b11001000 0
0&
#60
0!
#65
b10011100010000 '
b10011100010000 ,
1!
1&
0$
#70
0!
#75
b11111111 )
b11111111 .
b11111111 3
b1111111000000001 +
b1111111000000001 -
b11111111 *
b11111111 /
b11111111 1
1!
1%
1$
b11111111 #
b11111111 2
b11111111 "
b11111111 0
0&
#80
0!
#85
b1111111000000001 '
b1111111000000001 ,
1!
1&
0%
0$
#90
0!
#95
b1 )
b1 .
b1 3
b1111111111111111 +
b1111111111111111 -
b1111111111111111 *
b1111111111111111 /
b1111111111111111 1
1!
1%
1$
b1 #
b1 2
b1111111111111111 "
b1111111111111111 0
0&
#100
0!
#105
b1111111111111111 '
b1111111111111111 ,
1!
1&
0%
0$
#110
0!
#115
b1000110111 )
b1000110111 .
b1000110111 3
b10101010110100011110 +
b10101010110100011110 -
b10011010010 *
b10011010010 /
b10011010010 1
1!
1%
1$
b1000110111 #
b1000110111 2
b10011010010 "
b10011010010 0
0&
#120
0!
#125
b10101010110100011110 '
b10101010110100011110 ,
1!
1&
0%
0$
#130
0!
#135
b1010 )
b1010 .
b1010 3
b1111101000 +
b1111101000 -
b1100100 *
b1100100 /
b1100100 1
1!
1%
1$
b1010 #
b1010 2
b1100100 "
b1100100 0
0&
#140
0!
#145
b1111101000 '
b1111101000 ,
1!
1&
0%
0$
#150
0!
#155
1!
b101110111000 #
b101110111000 2
b11111010000 "
b11111010000 0
0&
#160
0!
#165
b11000000111001 *
b11000000111001 /
b11000000111001 1
b0 +
b0 -
b0 )
b0 .
b0 3
1!
1%
1$
b0 #
b0 2
b11000000111001 "
b11000000111001 0
#170
0!
#175
b0 '
b0 ,
1!
1&
0%
0$
#180
0!
#185
b1001101 *
b1001101 /
b1001101 1
b1101001111000 +
b1101001111000 -
b1011000 )
b1011000 .
b1011000 3
1!
1%
1$
b1011000 #
b1011000 2
b1001101 "
b1001101 0
0&
#190
0!
#195
b1101001111000 '
b1101001111000 ,
1!
1&
0%
0$
#200
0!
#205
b1011000 *
b1011000 /
b1011000 1
b1101001111000 +
b1101001111000 -
b1001101 )
b1001101 .
b1001101 3
1!
1%
1$
b1001101 #
b1001101 2
b1011000 "
b1011000 0
0&
#210
0!
#215
1!
1&
0%
0$
#220
0!
#225
b100101100 *
b100101100 /
b100101100 1
b111010100110000 +
b111010100110000 -
b1100100 )
b1100100 .
b1100100 3
1!
1%
1$
b1100100 #
b1100100 2
b100101100 "
b100101100 0
0&
#230
0!
#235
b111010100110000 '
b111010100110000 ,
1!
1&
0%
0$
#240
0!
#245
b0 *
b0 /
b0 1
b0 +
b0 -
b0 )
b0 .
b0 3
b0 '
b0 ,
1!
0(
0&
#250
0!
#255
b1101101100011000 +
b1101101100011000 -
b111001000 )
b111001000 .
b111001000 3
b1111011 *
b1111011 /
b1111011 1
1!
1%
1$
b111001000 #
b111001000 2
b1111011 "
b1111011 0
1(
#260
0!
#265
b1101101100011000 '
b1101101100011000 ,
1!
1&
0%
0$
#270
0!
#275
b1111111111111111 )
b1111111111111111 .
b1111111111111111 3
b1111111111111111 +
b1111111111111111 -
b1 *
b1 /
b1 1
1!
1%
1$
b1111111111111111 #
b1111111111111111 2
b1 "
b1 0
0&
#280
0!
#285
b1111111111111111 '
b1111111111111111 ,
1!
1&
0%
0$
#290
0!
#295
b10 )
b10 .
b10 3
b1111111111111110 +
b1111111111111110 -
b111111111111111 *
b111111111111111 /
b111111111111111 1
1!
1%
1$
b10 #
b10 2
b111111111111111 "
b111111111111111 0
0&
#300
0!
#305
b1111111111111110 '
b1111111111111110 ,
1!
1&
0%
0$
#310
0!
#315
1!
0&
